hypothesis_typed/__init__.py
hypothesis_typed-1.0.0.dist-info/WHEEL
hypothesis_typed-1.0.0.dist-info/METADATA
hypothesis_typed-1.0.0.dist-info/RECORD
