Metadata-Version: 2.1
Name: hypothesis-typed
Version: 1.0.0
Summary: An alias for hypothesis-auto
License: MIT
Author: Timothy Crosley
Author-email: timothy.crosley@gmail.com
Requires-Python: >=3.6,<4.0
Classifier: License :: OSI Approved :: MIT License
Classifier: Programming Language :: Python :: 3
Classifier: Programming Language :: Python :: 3.6
Classifier: Programming Language :: Python :: 3.7
Requires-Dist: hypothesis_auto (>=1.0,<2.0)
